mgcont/__init__.py
mgcont/__main__.py
mgcont/container.py
mgcont/docker_run.py
mgcont/docker_utils.py
mgcont/paths.py
mgcont/submission_dir.py
mgcont-1.0.4.dist-info/LICENSE
mgcont-1.0.4.dist-info/METADATA
mgcont-1.0.4.dist-info/WHEEL
mgcont-1.0.4.dist-info/entry_points.txt
mgcont-1.0.4.dist-info/top_level.txt
mgcont-1.0.4.dist-info/RECORD
