Metadata-Version: 2.1
Name: mgcont
Version: 1.0.4
Summary: Creates an exercise grading container
Home-page: https://github.com/teemulehtinen/mooc-grader-cont
Author: Teemu Lehtinen
Author-email: teemu.t.lehtinen@aalto.fi
Classifier: Programming Language :: Python :: 3
Classifier: License :: OSI Approved :: MIT License
Classifier: Operating System :: OS Independent
Requires-Python: >=3.6
License-File: LICENSE
Requires-Dist: pyyaml
Requires-Dist: docker
